ucamlookup/__init__.py
ucamlookup/admin.py
ucamlookup/apps.py
ucamlookup/forms.py
ucamlookup/ibisclient.py
ucamlookup/models.py
ucamlookup/signals.py
ucamlookup/tests.py
ucamlookup/urls.py
ucamlookup/utils.py
ucamlookup/views.py
ucamlookup/migrations/0001_initial.py
ucamlookup/migrations/__init__.py
ucamlookup/static/jquery-3.3.1.min.js
ucamlookup/static/select2-4.0.6-rc.1.full.min.js
ucamlookup/static/select2-4.0.6-rc.1.min.css
ucamlookup/templates/ucamlookup_groups.html
ucamlookup/templates/ucamlookup_headers.html
ucamlookup/templates/ucamlookup_users.html
ucamlookup/templates/admin/auth/lookup_group/add_form.html
ucamlookup/templates/admin/auth/lookup_user/add_form.html
ucamlookup/templatetags/__init__.py
ucamlookup/templatetags/dictionary_tag.py
django_ucamlookup-3.1.0.dist-info/AUTHORS
django_ucamlookup-3.1.0.dist-info/LICENSE
django_ucamlookup-3.1.0.dist-info/METADATA
django_ucamlookup-3.1.0.dist-info/WHEEL
django_ucamlookup-3.1.0.dist-info/top_level.txt
django_ucamlookup-3.1.0.dist-info/RECORD
