Metadata-Version: 2.1
Name: django-ucamlookup
Version: 3.1.0
Summary: A Django module for the University of Cambridge Lookup service
Home-page: https://gitlab.developers.cam.ac.uk/uis/devops/django/ucamlookup
Author: DevOps Division, University Information Services, University of Cambridge
Author-email: devops@uis.cam.ac.uk
License: MIT
Classifier: Development Status :: 5 - Production/Stable
Classifier: Environment :: Web Environment
Classifier: Framework :: Django
Classifier: Intended Audience :: Developers
Classifier: License :: OSI Approved :: MIT License
Classifier: Operating System :: OS Independent
Classifier: Programming Language :: Python
License-File: LICENSE
License-File: AUTHORS
Requires-Dist: django >=3.2
Requires-Dist: ibisclient ~=1.3
